.dockerignore
.gitignore
API.md
LICENSE
MANIFEST.in
README.md
gendoc.py
requirements.txt
setup.py
.circleci/config.yml
redisearch/__init__.py
redisearch/_util.py
redisearch/aggregation.py
redisearch/auto_complete.py
redisearch/client.py
redisearch/document.py
redisearch/query.py
redisearch/querystring.py
redisearch/reducers.py
redisearch/result.py
redisearch.egg-info/PKG-INFO
redisearch.egg-info/SOURCES.txt
redisearch.egg-info/dependency_links.txt
redisearch.egg-info/requires.txt
redisearch.egg-info/top_level.txt
test/test-setup.sh
test/test.py
test/test_builder.py
test/titles.csv
test/will_play_text.csv.bz2
test/docker/Dockerfile
test/docker/Makefile
test/docker/test.sh