Metadata-Version: 2.1
Name: redisearch
Version: 2.0.0
Summary: RedisSearch Python Client
Home-page: http://github.com/RedisLabs/redisearch-py
Author: RedisLabs
Author-email: oss@redislabs.com
License: UNKNOWN
Keywords: R,e,d,i,s, ,S,e,a,r,c,h, ,E,x,t,e,n,s,i,o,n
Platform: UNKNOWN
Classifier: Development Status :: 4 - Beta
Classifier: Intended Audience :: Developers
Classifier: License :: OSI Approved :: BSD License
Classifier: Programming Language :: Python :: 2.7
Classifier: Topic :: Database
Classifier: Topic :: Software Development :: Testing
